AUTHORS
ChangeLog
LICENSE
Readme.rst
requirements.txt
setup.cfg
setup.py
tox.ini
pyudpscan/__init__.py
pyudpscan/main.py
pyudpscan/scanner.py
pyudpscan.egg-info/PKG-INFO
pyudpscan.egg-info/SOURCES.txt
pyudpscan.egg-info/dependency_links.txt
pyudpscan.egg-info/entry_points.txt
pyudpscan.egg-info/not-zip-safe
pyudpscan.egg-info/pbr.json
pyudpscan.egg-info/requires.txt
pyudpscan.egg-info/top_level.txt